enumer/__init__.py
enumer/enumer.py
enumer/db/__init__.py
enumer/db/utils.py
enumer/test/__init__.py
enumer/test/sanity_checks.py
enumer-0.1.3.data/data/requirements.txt
enumer-0.1.3.dist-info/METADATA
enumer-0.1.3.dist-info/WHEEL
enumer-0.1.3.dist-info/top_level.txt
enumer-0.1.3.dist-info/RECORD
