Metadata-Version: 2.1
Name: enumer
Version: 0.1.3
Summary: Residue class enumeration given partial information of either end.
Home-page: https://github.com/Cosmic-Excalibur/enumer
Author: Astrageldon
Author-email: astrageldon@gmail.com
License: UNKNOWN
Platform: UNKNOWN
Classifier: Programming Language :: Python :: 3
Classifier: License :: OSI Approved :: MIT License
Classifier: Operating System :: OS Independent
Requires-Python: >=3.9
